end.py
end-1.3.1.dist-info/DESCRIPTION.rst
end-1.3.1.dist-info/METADATA
end-1.3.1.dist-info/RECORD
end-1.3.1.dist-info/WHEEL
end-1.3.1.dist-info/metadata.json
end-1.3.1.dist-info/top_level.txt
