Metadata-Version: 1.1
Name: end
Version: 1.3.1
Summary: Introduces "end" keyword to Python.
Home-page: https://github.com/nya3jp/end/
Author: Shuhei Takahashi
Author-email: takahashi.shuhei@gmail.com
License: UNKNOWN
Platform: UNKNOWN
Classifier: Operating System :: OS Independent
Classifier: Programming Language :: Python :: 2.7
Classifier: Programming Language :: Python :: 3.3
Classifier: Programming Language :: Python :: 3.4
Classifier: Programming Language :: Python :: 3.5
Classifier: License :: OSI Approved :: Apache Software License
Classifier: Topic :: Software Development :: Libraries :: Python Modules
